Metadata-Version: 2.1
Name: holehe
Version: 1.60.3
Summary: holehe allows you to check if the mail is used on different sites like twitter, instagram , snapchat and will retrieve information on sites with the forgotten password function.
Home-page: http://github.com/megadose/holehe
Author: megadose
Author-email: megadose@protonmail.com
License: UNKNOWN
Platform: UNKNOWN
Classifier: Programming Language :: Python
Classifier: License :: OSI Approved :: GNU General Public License v3 (GPLv3)
Requires-Dist: argparse
Requires-Dist: bs4
Requires-Dist: colorama
Requires-Dist: httpx
Requires-Dist: termcolor
Requires-Dist: tqdm
Requires-Dist: trio
